{
  "doctype": "Fee Structure",
  "timestamp": "2025-09-22T05:23:35.119Z",
  "count": 1,
  "data": [
    {
      "name": "EDU-FST-2025-00009",
      "owner": "Administrator",
      "creation": "2025-09-18 18:13:50.436813",
      "modified": "2025-09-18 18:14:23.829995",
      "modified_by": "Administrator",
      "docstatus": 1,
      "idx": 0,
      "naming_series": "EDU-FST-.YYYY.-",
      "program": "10 STD",
      "student_category": "Regular",
      "academic_year": "2025-2026",
      "academic_term": "2025-2026 (Term 1)",
      "total_amount": 17720,
      "receivable_account": "Debtors - SRS",
      "custom_income_account": "Cash - IBS",
      "company": "Sai Ravindra School",
      "cost_center": "Main - SRS",
      "doctype": "Fee Structure",
      "components": [
        {
          "name": "sa04tl4399",
          "owner": "Administrator",
          "creation": "2025-09-18 18:13:50.436813",
          "modified": "2025-09-18 18:14:23.829995",
          "modified_by": "Administrator",
          "docstatus": 1,
          "idx": 1,
          "fees_category": "Tuition",
          "amount": 10000,
          "item": "Tuition",
          "discount": 5,
          "total": 9500,
          "parent": "EDU-FST-2025-00009",
          "parentfield": "components",
          "parenttype": "Fee Structure",
          "doctype": "Fee Component"
        },
        {
          "name": "sa02f67vg7",
          "owner": "Administrator",
          "creation": "2025-09-18 18:13:50.436813",
          "modified": "2025-09-18 18:14:23.829995",
          "modified_by": "Administrator",
          "docstatus": 1,
          "idx": 2,
          "fees_category": "Transport",
          "amount": 4000,
          "item": "Transport",
          "discount": 4,
          "total": 3840,
          "parent": "EDU-FST-2025-00009",
          "parentfield": "components",
          "parenttype": "Fee Structure",
          "doctype": "Fee Component"
        },
        {
          "name": "sa0rmeshno",
          "owner": "Administrator",
          "creation": "2025-09-18 18:13:50.436813",
          "modified": "2025-09-18 18:14:23.829995",
          "modified_by": "Administrator",
          "docstatus": 1,
          "idx": 3,
          "fees_category": "Books",
          "amount": 3000,
          "item": "Books",
          "discount": 3,
          "total": 2910,
          "parent": "EDU-FST-2025-00009",
          "parentfield": "components",
          "parenttype": "Fee Structure",
          "doctype": "Fee Component"
        },
        {
          "name": "sa0en07ofa",
          "owner": "Administrator",
          "creation": "2025-09-18 18:13:50.436813",
          "modified": "2025-09-18 18:14:23.829995",
          "modified_by": "Administrator",
          "docstatus": 1,
          "idx": 4,
          "fees_category": "Stationary",
          "amount": 1500,
          "item": "Stationary",
          "discount": 2,
          "total": 1470,
          "parent": "EDU-FST-2025-00009",
          "parentfield": "components",
          "parenttype": "Fee Structure",
          "doctype": "Fee Component"
        }
      ]
    }
  ]
}